demo/__init__.py
demo/models.py
demo/settings.py
demo/tests.py
demo/urls.py
demo/wsgi.py
demo/migrations/0001_initial.py
demo/migrations/__init__.py
wagtail_hallo_plugins/__init__.py
wagtail_hallo_plugins/wagtail_hooks.py
wagtail_hallo_plugins/static/wagtail_hallo_plugins/wagtail_hallo_plugins.js
wagtail_hallo_plugins-1.0.2.dist-info/DESCRIPTION.rst
wagtail_hallo_plugins-1.0.2.dist-info/METADATA
wagtail_hallo_plugins-1.0.2.dist-info/RECORD
wagtail_hallo_plugins-1.0.2.dist-info/WHEEL
wagtail_hallo_plugins-1.0.2.dist-info/metadata.json
wagtail_hallo_plugins-1.0.2.dist-info/top_level.txt
